super_baso_kontol/__init__.py
super_baso_kontol/__main__.py
super_baso_kontol/cli.py
super_baso_kontol-1.2.1.dist-info/METADATA
super_baso_kontol-1.2.1.dist-info/WHEEL
super_baso_kontol-1.2.1.dist-info/entry_points.txt
super_baso_kontol-1.2.1.dist-info/top_level.txt
super_baso_kontol-1.2.1.dist-info/RECORD
